{
  "name": "Miscellaneous",
  "description": "A list of resources that cover a wide range of topics, not specific to any programming language.",
  "resources": [
    {
      "name": "Every link I wish I had as a beginner",
      "url": "https://github.com/kealanparr/Every-link-I-wish-I-had-as-a-beginner",
      "price": "Mostly free, some paid resources are included",
      "pros": [
	"A huge collection of useful links"
	],
      "cons": [
	"Can be overwhelming and hard to navigate"
	]
    }
  ]
}